{
  "db_name": "PostgreSQL",
  "query": "INSERT INTO async_players (series, event, player, kind, time, vod) VALUES ($1, $2, $3, $4, $5, $6) ON CONFLICT (series, event, player, kind) DO UPDATE SET time = EXCLUDED.time, vod = COALESCE(EXCLUDED.vod, async_players.vod)",
  "describe": {
    "columns": [],
    "parameters": {
      "Left": [
        "Varchar",
        "Varchar",
        "Int8",
        {
          "Custom": {
            "name": "async_kind",
            "kind": {
              "Enum": [
                "qualifier",
                "qualifier2",
                "qualifier3",
                "tiebreaker1",
                "tiebreaker2"
              ]
            }
          }
        },
        "Interval",
        "Text"
      ]
    },
    "nullable": []
  },
  "hash": "1a67e85e04fcd638a80cf51915eab8586617529da1e67e1b9839bf8b2bcba217"
}
