{
  "db_name": "PostgreSQL",
  "query": "SELECT id AS \"id: Id<Races>\"\n            FROM races\n            WHERE volunteer_request_message_id = $1\n              AND ignored = false\n            ORDER BY start ASC NULLS LAST",
  "describe": {
    "columns": [
      {
        "ordinal": 0,
        "name": "id: Id<Races>",
        "type_info": "Int8"
      }
    ],
    "parameters": {
      "Left": [
        "Int8"
      ]
    },
    "nullable": [
      false
    ]
  },
  "hash": "5f10cb322176baa239612d6cde3715195f9580371f4370a79042fc18a88b047f"
}
